dayhoff_tools/__init__.py
dayhoff_tools/batch/__init__.py
dayhoff_tools/batch/workers/__init__.py
dayhoff_tools/batch/workers/base.py
dayhoff_tools/batch/workers/boltz.py
dayhoff_tools/batch/workers/embed_t5.py
dayhoff_tools/chemistry/standardizer.py
dayhoff_tools/chemistry/utils.py
dayhoff_tools/cli/__init__.py
dayhoff_tools/cli/batch/__init__.py
dayhoff_tools/cli/batch/aws_batch.py
dayhoff_tools/cli/batch/commands/__init__.py
dayhoff_tools/cli/batch/commands/boltz.py
dayhoff_tools/cli/batch/commands/cancel.py
dayhoff_tools/cli/batch/commands/clean.py
dayhoff_tools/cli/batch/commands/embed_t5.py
dayhoff_tools/cli/batch/commands/finalize.py
dayhoff_tools/cli/batch/commands/list_jobs.py
dayhoff_tools/cli/batch/commands/local.py
dayhoff_tools/cli/batch/commands/logs.py
dayhoff_tools/cli/batch/commands/retry.py
dayhoff_tools/cli/batch/commands/status.py
dayhoff_tools/cli/batch/commands/submit.py
dayhoff_tools/cli/batch/job_id.py
dayhoff_tools/cli/batch/manifest.py
dayhoff_tools/cli/cloud_commands.py
dayhoff_tools/cli/engine1/__init__.py
dayhoff_tools/cli/engine1/engine_core.py
dayhoff_tools/cli/engine1/engine_lifecycle.py
dayhoff_tools/cli/engine1/engine_maintenance.py
dayhoff_tools/cli/engine1/engine_management.py
dayhoff_tools/cli/engine1/shared.py
dayhoff_tools/cli/engine1/studio_commands.py
dayhoff_tools/cli/engines_studios/__init__.py
dayhoff_tools/cli/engines_studios/api_client.py
dayhoff_tools/cli/engines_studios/auth.py
dayhoff_tools/cli/engines_studios/engine-studio-cli.md
dayhoff_tools/cli/engines_studios/engine_commands.py
dayhoff_tools/cli/engines_studios/progress.py
dayhoff_tools/cli/engines_studios/simulators/cli-simulators.md
dayhoff_tools/cli/engines_studios/simulators/demo.sh
dayhoff_tools/cli/engines_studios/simulators/engine_list_simulator.py
dayhoff_tools/cli/engines_studios/simulators/engine_status_simulator.py
dayhoff_tools/cli/engines_studios/simulators/idle_status_simulator.py
dayhoff_tools/cli/engines_studios/simulators/simulator_utils.py
dayhoff_tools-1.15.0.dist-info/METADATA
dayhoff_tools-1.15.0.dist-info/WHEEL
dayhoff_tools-1.15.0.dist-info/entry_points.txt
dayhoff_tools-1.15.0.dist-info/RECORD
